{
  "id": "48-laws-of-power-the-robert-greene--2",
  "workId": "48-laws-of-power-the-robert-greene",
  "jurisdictionId": "wisconsin",
  "governingBody": "Wisconsin corrections agencies and prison mailrooms",
  "dateText": "Date not yet pinned down",
  "startYear": null,
  "endYear": null,
  "actionType": "excluded from prison circulation",
  "reasonTags": [
    "instructional-harm",
    "public-order"
  ],
  "reasonSummary": "The Wisconsin prison-ban record treats the book as excluded reading inside state custody, which shows how prison and mailroom censorship function as a government reading regime. The exported reason says: security chief.",
  "note": "The Wisconsin prison-ban record treats the book as excluded reading inside state custody, which shows how prison and mailroom censorship function as a government reading regime. The exported reason says: security chief Westfield 309.04 (4) c.8. b.c.",
  "quotation": null,
  "sourceIds": [
    "marshall-project-prison-bans"
  ],
  "reviewStatus": "verified"
}
