{
  "id": "best-sm-erotica-more-extreme-tales-of-sex-volume-2-m-christian--1",
  "workId": "best-sm-erotica-more-extreme-tales-of-sex-volume-2-m-christian",
  "jurisdictionId": "wisconsin",
  "governingBody": "Wisconsin corrections agencies and prison mailrooms",
  "dateText": "2008-04-04",
  "startYear": 2008,
  "endYear": null,
  "actionType": "excluded from prison circulation",
  "reasonTags": [
    "obscenity",
    "public-morality"
  ],
  "reasonSummary": "The Wisconsin prison-ban record treats the book as excluded reading inside state custody, which shows how prison and mailroom censorship function as a government reading regime. The exported reason says: 309.04(4) 8.a.c.",
  "note": "The Wisconsin prison-ban record treats the book as excluded reading inside state custody, which shows how prison and mailroom censorship function as a government reading regime. The exported reason says: 309.04(4) 8.a.c.",
  "quotation": null,
  "sourceIds": [
    "marshall-project-prison-bans"
  ],
  "reviewStatus": "verified"
}
