{
  "id": "blow-him-away-marcy-michaels--1",
  "workId": "blow-him-away-marcy-michaels",
  "jurisdictionId": "texas",
  "governingBody": "Texas corrections agencies and prison mailrooms",
  "dateText": "2007-03-13",
  "startYear": 2007,
  "endYear": null,
  "actionType": "excluded from prison circulation",
  "reasonTags": [
    "obscenity",
    "public-morality"
  ],
  "reasonSummary": "The Texas prison-ban record treats the book as excluded reading inside state custody, which shows how prison and mailroom censorship function as a government reading regime. The exported reason says: PGS 100 & 102.",
  "note": "The Texas prison-ban record treats the book as excluded reading inside state custody, which shows how prison and mailroom censorship function as a government reading regime. The exported reason says: PGS 100 & 102 SEXUALLY EXPLICIT IMAGES",
  "quotation": null,
  "sourceIds": [
    "marshall-project-prison-bans"
  ],
  "reviewStatus": "verified"
}
