{
  "id": "bomb-maker-the-thomas-perry--1",
  "workId": "bomb-maker-the-thomas-perry",
  "jurisdictionId": "texas",
  "governingBody": "Texas corrections agencies and prison mailrooms",
  "dateText": "2018-06-28",
  "startYear": 2018,
  "endYear": null,
  "actionType": "excluded from prison circulation",
  "reasonTags": [
    "instructional-harm",
    "public-order"
  ],
  "reasonSummary": "The Texas prison-ban record treats the book as excluded reading inside state custody, which shows how prison and mailroom censorship function as a government reading regime. The exported reason says: PGS 71-73 MFG EXP",
  "note": "The Texas prison-ban record treats the book as excluded reading inside state custody, which shows how prison and mailroom censorship function as a government reading regime. The exported reason says: PGS 71-73 MFG EXP",
  "quotation": null,
  "sourceIds": [
    "marshall-project-prison-bans"
  ],
  "reviewStatus": "verified"
}
