{
  "id": "camp-life-in-the-woods-and-the-tricks-of-trapping-w-hamilton-gipson--1",
  "workId": "camp-life-in-the-woods-and-the-tricks-of-trapping-w-hamilton-gipson",
  "jurisdictionId": "wisconsin",
  "governingBody": "Wisconsin corrections agencies and prison mailrooms",
  "dateText": "2015-02-10",
  "startYear": 2015,
  "endYear": null,
  "actionType": "excluded from prison circulation",
  "reasonTags": [
    "instructional-harm",
    "public-order"
  ],
  "reasonSummary": "The Wisconsin prison-ban record treats the book as excluded reading inside state custody, which shows how prison and mailroom censorship function as a government reading regime. The exported reason says: DOC 309.05 2.",
  "note": "The Wisconsin prison-ban record treats the book as excluded reading inside state custody, which shows how prison and mailroom censorship function as a government reading regime. The exported reason says: DOC 309.05 2 (b) 5. Teach or describe the manufacture.",
  "quotation": null,
  "sourceIds": [
    "marshall-project-prison-bans"
  ],
  "reviewStatus": "verified"
}
