{
  "id": "candy-terry-southern-mason-hoffenberg--1",
  "workId": "candy-terry-southern-mason-hoffenberg",
  "jurisdictionId": "new-zealand",
  "governingBody": "Indecent Publications Tribunal",
  "dateText": "1969",
  "startYear": 1969,
  "endYear": null,
  "actionType": "classified, prohibited, or restricted",
  "reasonTags": [
    "obscenity",
    "public-morality"
  ],
  "reasonSummary": "Ruled indecent in 1969.",
  "note": "Ruled indecent in 1969.",
  "quotation": null,
  "sourceIds": [
    "wikipedia-books-banned-new-zealand"
  ],
  "reviewStatus": "verified"
}
