{
  "id": "cosmos-glow-in-the-dark-kama-sutra-none--1",
  "workId": "cosmos-glow-in-the-dark-kama-sutra-none",
  "jurisdictionId": "texas",
  "governingBody": "Texas corrections agencies and prison mailrooms",
  "dateText": "2021-05-07",
  "startYear": 2021,
  "endYear": null,
  "actionType": "excluded from prison circulation",
  "reasonTags": [
    "obscenity",
    "public-morality"
  ],
  "reasonSummary": "The Texas prison-ban record treats the book as excluded reading inside state custody, which shows how prison and mailroom censorship function as a government reading regime. The exported reason says: ENTIRE BOOK.",
  "note": "The Texas prison-ban record treats the book as excluded reading inside state custody, which shows how prison and mailroom censorship function as a government reading regime. The exported reason says: ENTIRE BOOK SEXUALLY EXPLICIT IMAGES",
  "quotation": null,
  "sourceIds": [
    "marshall-project-prison-bans"
  ],
  "reviewStatus": "verified"
}
