{
  "id": "dark-rising-the-art-of-aly-fell-aly-fell--1",
  "workId": "dark-rising-the-art-of-aly-fell-aly-fell",
  "jurisdictionId": "texas",
  "governingBody": "Texas corrections agencies and prison mailrooms",
  "dateText": "2013-10-31",
  "startYear": 2013,
  "endYear": null,
  "actionType": "excluded from prison circulation",
  "reasonTags": [
    "obscenity",
    "public-morality"
  ],
  "reasonSummary": "The Texas prison-ban record treats the book as excluded reading inside state custody, which shows how prison and mailroom censorship function as a government reading regime. The exported reason says: PAGES 6, 44, 45 &.",
  "note": "The Texas prison-ban record treats the book as excluded reading inside state custody, which shows how prison and mailroom censorship function as a government reading regime. The exported reason says: PAGES 6, 44, 45 & 49 SEXUALLY EXPLICIT IMAGES",
  "quotation": null,
  "sourceIds": [
    "marshall-project-prison-bans"
  ],
  "reviewStatus": "verified"
}
