{
  "id": "diamond-syndocate-erica-hilton--1",
  "workId": "diamond-syndocate-erica-hilton",
  "jurisdictionId": "texas",
  "governingBody": "Texas corrections agencies and prison mailrooms",
  "dateText": "2010-12-03",
  "startYear": 2010,
  "endYear": null,
  "actionType": "excluded from prison circulation",
  "reasonTags": [
    "instructional-harm",
    "public-order"
  ],
  "reasonSummary": "The Texas prison-ban record treats the book as excluded reading inside state custody, which shows how prison and mailroom censorship function as a government reading regime. The exported reason says: PG 65 SEX W/MINOR.",
  "note": "The Texas prison-ban record treats the book as excluded reading inside state custody, which shows how prison and mailroom censorship function as a government reading regime. The exported reason says: PG 65 SEX W/MINOR (AGE PG 65)",
  "quotation": null,
  "sourceIds": [
    "marshall-project-prison-bans"
  ],
  "reviewStatus": "verified"
}
