{
  "id": "failure-to-appear-ja-jance--2",
  "workId": "failure-to-appear-ja-jance",
  "jurisdictionId": "texas",
  "governingBody": "Texas corrections agencies and prison mailrooms",
  "dateText": "2014-11-17",
  "startYear": 2014,
  "endYear": null,
  "actionType": "excluded from prison circulation",
  "reasonTags": [
    "instructional-harm",
    "public-order"
  ],
  "reasonSummary": "The Texas prison-ban record treats the book as excluded reading inside state custody, which shows how prison and mailroom censorship function as a government reading regime. The exported reason says: PG 142 INCEST.",
  "note": "The Texas prison-ban record treats the book as excluded reading inside state custody, which shows how prison and mailroom censorship function as a government reading regime. The exported reason says: PG 142 INCEST FTR/DTR",
  "quotation": null,
  "sourceIds": [
    "marshall-project-prison-bans"
  ],
  "reviewStatus": "verified"
}
