{
  "id": "fetishisms-sexy-wives-takumi-adachi--1",
  "workId": "fetishisms-sexy-wives-takumi-adachi",
  "jurisdictionId": "texas",
  "governingBody": "Texas corrections agencies and prison mailrooms",
  "dateText": "2018-08-07",
  "startYear": 2018,
  "endYear": null,
  "actionType": "excluded from prison circulation",
  "reasonTags": [
    "obscenity",
    "public-morality"
  ],
  "reasonSummary": "The Texas prison-ban record treats the book as excluded reading inside state custody, which shows how prison and mailroom censorship function as a government reading regime. The exported reason says: PGS 10, 11, 20 &.",
  "note": "The Texas prison-ban record treats the book as excluded reading inside state custody, which shows how prison and mailroom censorship function as a government reading regime. The exported reason says: PGS 10, 11, 20 & 21 SEXUALLY EXPLICIT IMAGES",
  "quotation": null,
  "sourceIds": [
    "marshall-project-prison-bans"
  ],
  "reviewStatus": "verified"
}
