{
  "id": "fugitive-game-jonahtan-littman--1",
  "workId": "fugitive-game-jonahtan-littman",
  "jurisdictionId": "michigan",
  "governingBody": "Michigan corrections agencies and prison mailrooms",
  "dateText": "1999-12-01",
  "startYear": 1999,
  "endYear": null,
  "actionType": "excluded from prison circulation",
  "reasonTags": [
    "instructional-harm",
    "public-order"
  ],
  "reasonSummary": "The Michigan prison-ban record treats the book as excluded reading inside state custody, which shows how prison and mailroom censorship function as a government reading regime. The exported reason says: Advocates.",
  "note": "The Michigan prison-ban record treats the book as excluded reading inside state custody, which shows how prison and mailroom censorship function as a government reading regime. The exported reason says: Advocates criminal activity",
  "quotation": null,
  "sourceIds": [
    "marshall-project-prison-bans"
  ],
  "reviewStatus": "verified"
}
