{
  "id": "in-n-girls-volume-2-akos-banfalvi--1",
  "workId": "in-n-girls-volume-2-akos-banfalvi",
  "jurisdictionId": "wisconsin",
  "governingBody": "Wisconsin corrections agencies and prison mailrooms",
  "dateText": "Date not yet pinned down",
  "startYear": null,
  "endYear": null,
  "actionType": "excluded from prison circulation",
  "reasonTags": [
    "instructional-harm",
    "obscenity",
    "public-morality",
    "public-order"
  ],
  "reasonSummary": "The Wisconsin prison-ban record treats the book as excluded reading inside state custody, which shows how prison and mailroom censorship function as a government reading regime. The exported reason says: 309.00.50.",
  "note": "The Wisconsin prison-ban record treats the book as excluded reading inside state custody, which shows how prison and mailroom censorship function as a government reading regime. The exported reason says: 309.00.50 Nudity in Commercially Published Material",
  "quotation": null,
  "sourceIds": [
    "marshall-project-prison-bans"
  ],
  "reviewStatus": "verified"
}
