{
  "id": "interest-kevin-gaughen--1",
  "workId": "interest-kevin-gaughen",
  "jurisdictionId": "indonesia",
  "governingBody": "Indonesia authorities",
  "dateText": "Date not yet pinned down",
  "startYear": null,
  "endYear": null,
  "actionType": "banned publication or circulation",
  "reasonTags": [
    "political-control",
    "political-dissent"
  ],
  "reasonSummary": "Banned by the government of Indonesia for subversive and/or anti-government themes.",
  "note": "Banned by the government of Indonesia for subversive and/or anti-government themes.",
  "quotation": null,
  "sourceIds": [
    "wikipedia-government-list"
  ],
  "reviewStatus": "verified"
}
