{
  "id": "rebirth-reformasi-resistance-and-hope-in-new-malaysia-kean-wong--1",
  "workId": "rebirth-reformasi-resistance-and-hope-in-new-malaysia-kean-wong",
  "jurisdictionId": "malaysia",
  "governingBody": "Malaysia authorities",
  "dateText": "Date not yet pinned down",
  "startYear": null,
  "endYear": null,
  "actionType": "banned publication or circulation",
  "reasonTags": [
    "political-sensitivity"
  ],
  "reasonSummary": "Banned for containing insulting elements to the Malaysian coat of arms which is likely to be prejudicial to public order, security, national interest, alarm public opinion and contrary to any law, and therefore is.",
  "note": "Banned for containing insulting elements to the Malaysian coat of arms which is likely to be prejudicial to public order, security, national interest, alarm public opinion and contrary to any law, and therefore is \"absolutely prohibited throughout Malaysia\".",
  "quotation": null,
  "sourceIds": [
    "wikipedia-government-list"
  ],
  "reviewStatus": "verified"
}
